ini_safedb_sdk/__init__.py
ini_safedb_sdk/client.py
ini_safedb_sdk/exceptions.py
ini_safedb_sdk/models.py
ini_safedb_sdk/retry.py
ini_safedb_sdk-1.0.0.dist-info/METADATA
ini_safedb_sdk-1.0.0.dist-info/WHEEL
ini_safedb_sdk-1.0.0.dist-info/RECORD
